ra_system/__init__.py
ra_system/constants.py
ra_system/gates.py
ra_system/omega.py
ra_system/rac.py
ra_system/repitans.py
ra_system/spherical.py
ra_system/ton.py
ra_system-0.1.0.dist-info/METADATA
ra_system-0.1.0.dist-info/WHEEL
ra_system-0.1.0.dist-info/RECORD
