Metadata-Version: 2.4
Name: ra-system
Version: 0.1.0
Summary: Ra System mathematical constants - Python bindings
Project-URL: Homepage, https://github.com/anywave/ra-system
Project-URL: Repository, https://github.com/anywave/ra-system.git
Author-email: Anywave <info@anywavecreations.com>
License-Expression: Apache-2.0
Keywords: constants,harmonics,mathematics,ra-system
Classifier: Development Status :: 3 - Alpha
Classifier: Intended Audience :: Science/Research
Classifier: License :: OSI Approved :: Apache Software License
Classifier: Programming Language :: Python :: 3
Classifier: Programming Language :: Python :: 3.10
Classifier: Programming Language :: Python :: 3.11
Classifier: Programming Language :: Python :: 3.12
Classifier: Topic :: Scientific/Engineering :: Mathematics
Classifier: Typing :: Typed
Requires-Python: >=3.10
Provides-Extra: dev
Requires-Dist: hypothesis>=6.0; extra == 'dev'
Requires-Dist: mypy>=1.0; extra == 'dev'
Requires-Dist: pytest-cov>=4.0; extra == 'dev'
Requires-Dist: pytest>=7.0; extra == 'dev'
Requires-Dist: ruff>=0.1; extra == 'dev'
